[ {
  "playerName" : "Tester",
  "score" : 300,
  "playedAt" : "2026-05-30T12:35:59"
}, {
  "playerName" : "Jon",
  "score" : 100,
  "playedAt" : "2026-05-30T12:40:31"
}, {
  "playerName" : "Christian",
  "score" : 700,
  "playedAt" : "2026-05-30T12:42:24"
}, {
  "playerName" : "Andres",
  "score" : 500,
  "playedAt" : "2026-05-30T12:42:24"
}, {
  "playerName" : "Test",
  "score" : 0,
  "playedAt" : "2026-05-30T12:44:00"
}, {
  "playerName" : "Test2",
  "score" : 0,
  "playedAt" : "2026-05-30T12:45:12"
}, {
  "playerName" : "Alice",
  "score" : 200,
  "playedAt" : "2026-05-30T13:13:03"
}, {
  "playerName" : "ChrisTest1",
  "score" : 200,
  "playedAt" : "2026-05-30T13:18:12"
}, {
  "playerName" : "1",
  "score" : 0,
  "playedAt" : "2026-05-30T13:48:00"
}, {
  "playerName" : "1",
  "score" : 0,
  "playedAt" : "2026-05-30T13:48:17"
}, {
  "playerName" : "1",
  "score" : 0,
  "playedAt" : "2026-05-30T13:48:32"
}, {
  "playerName" : "Test Player",
  "score" : 2400,
  "playedAt" : "2026-05-30T13:48:59"
}, {
  "playerName" : "ChrisTest2",
  "score" : 2100,
  "playedAt" : "2026-05-30T13:55:53"
} ]